README.md
setup.py
docker_fabric.egg-info/PKG-INFO
docker_fabric.egg-info/SOURCES.txt
docker_fabric.egg-info/dependency_links.txt
docker_fabric.egg-info/requires.txt
docker_fabric.egg-info/top_level.txt
dockerfabric/__init__.py
dockerfabric/actions.py
dockerfabric/api.py
dockerfabric/apiclient.py
dockerfabric/base.py
dockerfabric/cli.py
dockerfabric/socat.py
dockerfabric/tasks.py
dockerfabric/tunnel.py
dockerfabric/yaml.py
dockerfabric/utils/__init__.py
dockerfabric/utils/base.py
dockerfabric/utils/containers.py
dockerfabric/utils/files.py
dockerfabric/utils/net.py
dockerfabric/utils/output.py
dockerfabric/utils/users.py