Metadata-Version: 1.1
Name: docker-fabric
Version: 0.5.0
Summary: Build Docker images, and run Docker containers in Fabric.
Home-page: https://github.com/merll/docker-fabric
Author: Matthias Erll
Author-email: matthias@erll.de
License: MIT
Keywords: docker,fabric
Platform: OS Independent
Classifier: Environment :: Web Environment
Classifier: Intended Audience :: Developers
Classifier: License :: OSI Approved :: MIT License
Classifier: Operating System :: OS Independent
Classifier: Programming Language :: Python
Classifier: Topic :: Software Development :: Libraries :: Python Modules
Classifier: Topic :: Software Development :: Build Tools
Classifier: Topic :: System :: Software Distribution
Classifier: Development Status :: 4 - Beta
Classifier: Programming Language :: Python :: 2.7
